focus/Robot.py
focus/__init__.py
focus/__main__.py
focus/ui.py
focus_xp-0.1.1.dist-info/METADATA
focus_xp-0.1.1.dist-info/WHEEL
focus_xp-0.1.1.dist-info/top_level.txt
focus_xp-0.1.1.dist-info/RECORD
