Metadata-Version: 2.1
Name: focus-xp
Version: 0.1.1
Summary: focus package
Home-page: https://github.com/pxp511/focus
Author: xp9588
Author-email: 958876660@qq.com
License: UNKNOWN
Platform: any
